data_analysis_tools/__init__.py
data_analysis_tools/data.py
data_analysis_tools/models.py
data_analysis_tools/pandas_loader.py
data_analysis_tools/plot_tools.py
data_anlysis_tools/__init__.py
data_anlysis_tools/data.py
data_anlysis_tools/models.py
data_anlysis_tools/pandas_loader.py
data_anlysis_tools/plot_tools.py
data_analysis_tools-0.0.3.dist-info/LICENSE.txt
data_analysis_tools-0.0.3.dist-info/METADATA
data_analysis_tools-0.0.3.dist-info/WHEEL
data_analysis_tools-0.0.3.dist-info/top_level.txt
data_analysis_tools-0.0.3.dist-info/RECORD
