Metadata-Version: 2.1
Name: data-analysis-tools
Version: 0.0.3
Summary: Tools to read and analyse data files and Qudi data files.
Home-page: https://github.com/alrik-durand/data_analysis_tools
Author: Alrik Durand
Author-email: alrik.durand@gmail.com
License: GPLv3
Platform: UNKNOWN
Requires-Python: >=3.6
Requires-Dist: numpy
Requires-Dist: pandas
Requires-Dist: matplotlib
Requires-Dist: scipy
Requires-Dist: lmfit
